drf_iam/__init__.py
drf_iam/admin.py
drf_iam/apps.py
drf_iam/decorators.py
drf_iam/models.py
drf_iam/permissions.py
drf_iam/tests.py
drf_iam/migrations/0001_initial.py
drf_iam/migrations/0002_add_policy_name.py
drf_iam/migrations/__init__.py
drf_iam/utils/__init__.py
drf_iam/utils/load_viewset_permissions.py
drf_iam/utils/logging_utils.py
drf_iam-0.2.11.dist-info/METADATA
drf_iam-0.2.11.dist-info/WHEEL
drf_iam-0.2.11.dist-info/top_level.txt
drf_iam-0.2.11.dist-info/RECORD
